best/__init__.py
best/integration/__init__.py
best/unit/__init__.py
best/unit/conftest.py
best/unit/test_glue_session.py
best/unit/test_glue_session_demo.py
best/unit/test_session_apis.py
aws_iatk-119.4.6.dist-info/LICENSE.txt
aws_iatk-119.4.6.dist-info/METADATA
aws_iatk-119.4.6.dist-info/WHEEL
aws_iatk-119.4.6.dist-info/top_level.txt
aws_iatk-119.4.6.dist-info/RECORD
