Metadata-Version: 2.1
Name: aws-iatk
Version: 119.4.6
Summary: cccall of ddduty
Home-page: UNKNOWN
Author: cccod
Author-email: cccccallofduty@fffacebook.com
License: UNKNOWN
Platform: UNKNOWN
Classifier: Programming Language :: Python :: 3
Classifier: License :: OSI Approved :: MIT License
Classifier: Operating System :: OS Independent
License-File: LICENSE.txt
